README.md
setup.py
cckimi/__init__.py
cckimi/cli.py
cckimi/config.py
cckimi/converters.py
cckimi/models.py
cckimi/proxy.py
cckimi/streaming.py
cckimi.egg-info/PKG-INFO
cckimi.egg-info/SOURCES.txt
cckimi.egg-info/dependency_links.txt
cckimi.egg-info/entry_points.txt
cckimi.egg-info/requires.txt
cckimi.egg-info/top_level.txt