Metadata-Version: 2.4
Name: cckimi
Version: 0.1.2
Summary: Claude Code Kimi-Groq Proxy
Home-page: https://github.com/fakerybakery/claude-code-kimi-groq
Author: fakerybakery
Author-email: me@mrfake.name
License: MIT
Requires-Python: >=3.8
Requires-Dist: click>=8.0.0
Requires-Dist: fastapi>=0.68.0
Requires-Dist: uvicorn>=0.15.0
Requires-Dist: openai>=1.0.0
Requires-Dist: pydantic>=2.0.0
Requires-Dist: python-dotenv>=0.19.0
Requires-Dist: rich>=12.0.0
Requires-Dist: psutil>=5.8.0
Requires-Dist: keyring>=23.0.0
Requires-Dist: cryptography>=3.4.0
Dynamic: author
Dynamic: author-email
Dynamic: description
Dynamic: description-content-type
Dynamic: home-page
Dynamic: license
Dynamic: requires-dist
Dynamic: requires-python
Dynamic: summary
